andmath/GaussianProcess.py
andmath/GaussianProcessRegression.py
andmath/KMeansClustering.py
andmath/__init__.py
andmath/general_functions.py
tests/1D_KMeansClustering.py
tests/2D_KMeansClustering.py
tests/GaussianProcessRegression_1D.py
tests/KMeansClustering_1D.py
tests/KMeansClustering_2D.py
tests/__init__.py
tests/test_GaussianProcessRegression_1D.py
tests/test_GaussianProcessRegression_2D.py
tests/test_KMeansClustering_1D.py
tests/test_KMeansClustering_2D.py
andmath-1.0.9.dist-info/LICENSE
andmath-1.0.9.dist-info/METADATA
andmath-1.0.9.dist-info/WHEEL
andmath-1.0.9.dist-info/top_level.txt
andmath-1.0.9.dist-info/RECORD
