Metadata-Version: 2.1
Name: andmath
Version: 1.0.9
Summary: A small math and statistics package.
Home-page: https://github.com/pypa/sampleproject
Author: André Gerbaulet
Author-email: andregerbaulet@gmail.com
License: UNKNOWN
Platform: UNKNOWN
Classifier: Programming Language :: Python :: 3
Classifier: License :: OSI Approved :: MIT License
Classifier: Operating System :: OS Independent
Requires-Python: >=3.6
